hermes/__init__.py
hermes/counters.py
hermes/exceptions.py
hermes/gauges.py
hermes/hermes.py
hermes/histograms.py
hermes/models.py
hermes/summaries.py
python_hermes-0.0.4.dist-info/METADATA
python_hermes-0.0.4.dist-info/WHEEL
python_hermes-0.0.4.dist-info/top_level.txt
python_hermes-0.0.4.dist-info/RECORD
