Metadata-Version: 2.1
Name: python-hermes
Version: 0.0.4
Summary: Python client library for pushing metrics to Hermes server instance
Home-page: https://github.com/PSauerborn/hermes
Author: Pascal Sauerborn
Author-email: pascal.sauerborn@gmail.com
License: MIT
Platform: UNKNOWN
Classifier: License :: OSI Approved :: MIT License
Classifier: Programming Language :: Python :: 3
Classifier: Programming Language :: Python :: 3.8
Requires-Dist: pydantic
